{
 "R8R44A": {
  "_facts": {
   "unterkategorie": "Unmanaged Switch",
   "quell_url": "https://www.hpe.com/psnow/doc/a50004290enw",
   "verifiziert_am": "2026-07-02"
  },
  "artikelname": "Aruba Instant On 1430 5G R8R44A Unmanaged Switch (L2) – 5× 10/100/1000 (RJ45), Desktop-/Wandmontage",
  "titel_tag": "Aruba Instant On 1430 5G R8R44A | Hexwaren",
  "meta_description": "Original Aruba Instant On 1430 5G (R8R44A): unmanaged Layer-2-Switch mit 5× 10/100/1000 (RJ45), Switching-Kapazität 10 Gbit/s, ohne PoE, Plug-and-Play.",
  "artikelgewicht": "0,27",
  "versandgewicht": "2,27",
  "kurzbeschreibung": "<p>Der Aruba Instant On 1430 5G (R8R44A) ist ein unmanaged Layer-2-Switch der Aruba-Instant-On-1430-Serie mit 5 Ports, verwaltet ohne Konfiguration im Plug-and-Play-Betrieb.</p><p>Im Formfaktor Desktop-/Wandmontage liefert der R8R44A eine Switching-Kapazität von 10 Gbit/s und bindet per seine Gigabit-Ports an das Netz an. Er wird als versiegelte Original-Neuware geliefert.</p>",
  "intro": [
   "Der Aruba Instant On 1430 5G (R8R44A) ist ein unmanaged Layer-2-Switch aus der Aruba-Instant-On-1430-Familie mit 5 Ports (5× 10/100/1000 (RJ45)), ausgelegt für den einfachen, konfigurationsfreien Netzzugang.",
   "Mit 5 Ports erreicht der R8R44A eine Switching-Kapazität von 10 Gbit/s bei einer Weiterleitungsrate von 7,44 Mpps. Der R8R44A ist ein Modell ohne PoE und konzentriert sich auf reine Datenanbindung. Der R8R44A arbeitet als Plug-and-Play-Gerät ohne Management: keine Konfiguration, kein VLAN-Setup und kein Stacking – einstecken und betreiben.",
   "Im Formfaktor Desktop-/Wandmontage arbeitet der R8R44A im Temperaturbereich 0 bis 40 °C; für Kühlung und Stromversorgung des R8R44A sorgen Lüfterlos (passiv gekühlt) sowie Externes Steckernetzteil (im Lieferumfang). Der R8R44A bietet Layer-2-Plug-and-Play-Weiterleitung mit automatischem QoS (802.1p/DSCP), Flusssteuerung, Jumbo-Frames und Energy Efficient Ethernet – ohne Konfiguration. Geliefert wird der R8R44A als versiegelte Original-Neuware. Originaler HP-Switch."
  ],
  "kompatibilitaet": [
   "Plug-and-Play (kein Management erforderlich)"
  ],
  "faq": [
   [
    "Wie viele Ports hat der R8R44A?",
    "Der R8R44A bietet insgesamt 5 Ports: 5× 10/100/1000 (RJ45)."
   ],
   [
    "Unterstützt der R8R44A PoE?",
    "Nein. Der R8R44A ist ein Modell ohne Power over Ethernet und für reine Datenanbindung ausgelegt."
   ],
   [
    "Muss der R8R44A konfiguriert werden?",
    "Nein. Der R8R44A ist ein Unmanaged-Switch und arbeitet ohne Konfiguration im Plug-and-Play-Betrieb."
   ],
   [
    "Was zeichnet den R8R44A technisch aus?",
    "Der R8R44A bietet eine Switching-Kapazität von 10 Gbit/s und eine Weiterleitungsrate von 7,44 Mpps. Er bietet Layer-2-Plug-and-Play-Weiterleitung mit automatischem QoS (802.1p/DSCP), Flusssteuerung, Jumbo-Frames und Energy Efficient Ethernet – ohne Konfiguration. Für Stromversorgung und Kühlung des R8R44A sorgen Externes Steckernetzteil (im Lieferumfang) sowie Lüfterlos (passiv gekühlt)."
   ]
  ],
  "verwandte": [],
  "attributes": [
   [
    "Switch-Typ",
    "Unmanaged"
   ],
   [
    "Layer",
    "L2"
   ],
   [
    "Portanzahl",
    "5"
   ],
   [
    "Port-Konfiguration",
    "5× 10/100/1000 (RJ45)"
   ],
   [
    "Port-Geschwindigkeit",
    "10/100/1000 Mbit/s (RJ45)"
   ],
   [
    "Uplink-Ports",
    "Kein dedizierter Uplink (alle Ports gleichwertig nutzbar)"
   ],
   [
    "PoE",
    "Nein"
   ],
   [
    "Switching-Kapazität",
    "10 Gbit/s"
   ],
   [
    "Durchsatz",
    "7,44 Mpps"
   ],
   [
    "Bauform",
    "Desktop-/Wandmontage (kompakt)"
   ],
   [
    "Stromversorgung",
    "Externes Steckernetzteil (im Lieferumfang)"
   ],
   [
    "Kühlung",
    "Lüfterlos (passiv gekühlt)"
   ],
   [
    "Betriebstemperatur",
    "0 bis 40 °C"
   ],
   [
    "Anwendung",
    "Unmanaged SMB-/Heimbüro-Zugang (Layer 2, Plug-and-Play) ohne Management, für einfache Netzerweiterung"
   ],
   [
    "Zustand",
    "Neu, versiegelt"
   ]
  ],
  "provenance": {
   "Switch-Typ": [
    "https://www.hpe.com/psnow/doc/a50004290enw",
    "datasheet"
   ],
   "Layer": [
    "https://www.hpe.com/psnow/doc/a50004290enw",
    "datasheet"
   ],
   "Portanzahl": [
    "https://www.hpe.com/psnow/doc/a50004290enw",
    "datasheet"
   ],
   "Port-Konfiguration": [
    "https://www.hpe.com/psnow/doc/a50004290enw",
    "datasheet"
   ],
   "Port-Geschwindigkeit": [
    "https://www.hpe.com/psnow/doc/a50004290enw",
    "datasheet"
   ],
   "Uplink-Ports": [
    "https://www.hpe.com/psnow/doc/a50004290enw",
    "datasheet"
   ],
   "PoE": [
    "https://www.hpe.com/psnow/doc/a50004290enw",
    "datasheet"
   ],
   "Switching-Kapazität": [
    "https://www.hpe.com/psnow/doc/a50004290enw",
    "datasheet"
   ],
   "Durchsatz": [
    "https://www.hpe.com/psnow/doc/a50004290enw",
    "datasheet"
   ],
   "Bauform": [
    "https://www.hpe.com/psnow/doc/a50004290enw",
    "datasheet"
   ],
   "Stromversorgung": [
    "https://www.hpe.com/psnow/doc/a50004290enw",
    "datasheet"
   ],
   "Kühlung": [
    "https://www.hpe.com/psnow/doc/a50004290enw",
    "datasheet"
   ],
   "Betriebstemperatur": [
    "https://www.hpe.com/psnow/doc/a50004290enw",
    "datasheet"
   ],
   "Anwendung": [
    "https://www.hpe.com/psnow/doc/a50004290enw",
    "datasheet"
   ]
  },
  "netto_vk": "60.00"
 },
 "R8R45A": {
  "_facts": {
   "unterkategorie": "Unmanaged Switch",
   "quell_url": "https://www.hpe.com/psnow/doc/a50004290enw",
   "verifiziert_am": "2026-07-02"
  },
  "artikelname": "Aruba Instant On 1430 8G R8R45A Unmanaged Switch (L2) – 8× 10/100/1000 (RJ45), Desktop-/Wandmontage",
  "titel_tag": "Aruba Instant On 1430 8G R8R45A | Hexwaren",
  "meta_description": "Original Aruba Instant On 1430 8G (R8R45A): unmanaged Layer-2-Switch mit 8× 10/100/1000 (RJ45), Switching-Kapazität 16 Gbit/s, ohne PoE, Plug-and-Play.",
  "artikelgewicht": "0,59",
  "versandgewicht": "2,59",
  "kurzbeschreibung": "<p>Der Aruba Instant On 1430 8G (R8R45A) ist ein unmanaged Layer-2-Switch der Aruba-Instant-On-1430-Serie mit 8 Ports, verwaltet ohne Konfiguration im Plug-and-Play-Betrieb.</p><p>Im Formfaktor Desktop-/Wandmontage liefert der R8R45A eine Switching-Kapazität von 16 Gbit/s und bindet per seine Gigabit-Ports an das Netz an. Er wird als versiegelte Original-Neuware geliefert.</p>",
  "intro": [
   "Der Aruba Instant On 1430 8G (R8R45A) ist ein unmanaged Layer-2-Switch aus der Aruba-Instant-On-1430-Familie mit 8 Ports (8× 10/100/1000 (RJ45)), ausgelegt für den einfachen, konfigurationsfreien Netzzugang.",
   "Mit 8 Ports erreicht der R8R45A eine Switching-Kapazität von 16 Gbit/s bei einer Weiterleitungsrate von 11,90 Mpps. Der R8R45A ist ein Modell ohne PoE und konzentriert sich auf reine Datenanbindung. Der R8R45A arbeitet als Plug-and-Play-Gerät ohne Management: keine Konfiguration, kein VLAN-Setup und kein Stacking – einstecken und betreiben.",
   "Im Formfaktor Desktop-/Wandmontage arbeitet der R8R45A im Temperaturbereich 0 bis 40 °C; für Kühlung und Stromversorgung des R8R45A sorgen Lüfterlos (passiv gekühlt) sowie Externes Steckernetzteil (im Lieferumfang). Der R8R45A bietet Layer-2-Plug-and-Play-Weiterleitung mit automatischem QoS (802.1p/DSCP), Flusssteuerung, Jumbo-Frames und Energy Efficient Ethernet – ohne Konfiguration. Geliefert wird der R8R45A als versiegelte Original-Neuware. Originaler HP-Switch."
  ],
  "kompatibilitaet": [
   "Plug-and-Play (kein Management erforderlich)"
  ],
  "faq": [
   [
    "Wie viele Ports hat der R8R45A?",
    "Der R8R45A bietet insgesamt 8 Ports: 8× 10/100/1000 (RJ45)."
   ],
   [
    "Unterstützt der R8R45A PoE?",
    "Nein. Der R8R45A ist ein Modell ohne Power over Ethernet und für reine Datenanbindung ausgelegt."
   ],
   [
    "Muss der R8R45A konfiguriert werden?",
    "Nein. Der R8R45A ist ein Unmanaged-Switch und arbeitet ohne Konfiguration im Plug-and-Play-Betrieb."
   ],
   [
    "Was zeichnet den R8R45A technisch aus?",
    "Der R8R45A bietet eine Switching-Kapazität von 16 Gbit/s und eine Weiterleitungsrate von 11,90 Mpps. Er bietet Layer-2-Plug-and-Play-Weiterleitung mit automatischem QoS (802.1p/DSCP), Flusssteuerung, Jumbo-Frames und Energy Efficient Ethernet – ohne Konfiguration. Für Stromversorgung und Kühlung des R8R45A sorgen Externes Steckernetzteil (im Lieferumfang) sowie Lüfterlos (passiv gekühlt)."
   ]
  ],
  "verwandte": [],
  "attributes": [
   [
    "Switch-Typ",
    "Unmanaged"
   ],
   [
    "Layer",
    "L2"
   ],
   [
    "Portanzahl",
    "8"
   ],
   [
    "Port-Konfiguration",
    "8× 10/100/1000 (RJ45)"
   ],
   [
    "Port-Geschwindigkeit",
    "10/100/1000 Mbit/s (RJ45)"
   ],
   [
    "Uplink-Ports",
    "Kein dedizierter Uplink (alle Ports gleichwertig nutzbar)"
   ],
   [
    "PoE",
    "Nein"
   ],
   [
    "Switching-Kapazität",
    "16 Gbit/s"
   ],
   [
    "Durchsatz",
    "11,90 Mpps"
   ],
   [
    "Bauform",
    "Desktop-/Wandmontage (kompakt)"
   ],
   [
    "Stromversorgung",
    "Externes Steckernetzteil (im Lieferumfang)"
   ],
   [
    "Kühlung",
    "Lüfterlos (passiv gekühlt)"
   ],
   [
    "Betriebstemperatur",
    "0 bis 40 °C"
   ],
   [
    "Anwendung",
    "Unmanaged SMB-/Heimbüro-Zugang (Layer 2, Plug-and-Play) ohne Management, für einfache Netzerweiterung"
   ],
   [
    "Zustand",
    "Neu, versiegelt"
   ]
  ],
  "provenance": {
   "Switch-Typ": [
    "https://www.hpe.com/psnow/doc/a50004290enw",
    "datasheet"
   ],
   "Layer": [
    "https://www.hpe.com/psnow/doc/a50004290enw",
    "datasheet"
   ],
   "Portanzahl": [
    "https://www.hpe.com/psnow/doc/a50004290enw",
    "datasheet"
   ],
   "Port-Konfiguration": [
    "https://www.hpe.com/psnow/doc/a50004290enw",
    "datasheet"
   ],
   "Port-Geschwindigkeit": [
    "https://www.hpe.com/psnow/doc/a50004290enw",
    "datasheet"
   ],
   "Uplink-Ports": [
    "https://www.hpe.com/psnow/doc/a50004290enw",
    "datasheet"
   ],
   "PoE": [
    "https://www.hpe.com/psnow/doc/a50004290enw",
    "datasheet"
   ],
   "Switching-Kapazität": [
    "https://www.hpe.com/psnow/doc/a50004290enw",
    "datasheet"
   ],
   "Durchsatz": [
    "https://www.hpe.com/psnow/doc/a50004290enw",
    "datasheet"
   ],
   "Bauform": [
    "https://www.hpe.com/psnow/doc/a50004290enw",
    "datasheet"
   ],
   "Stromversorgung": [
    "https://www.hpe.com/psnow/doc/a50004290enw",
    "datasheet"
   ],
   "Kühlung": [
    "https://www.hpe.com/psnow/doc/a50004290enw",
    "datasheet"
   ],
   "Betriebstemperatur": [
    "https://www.hpe.com/psnow/doc/a50004290enw",
    "datasheet"
   ],
   "Anwendung": [
    "https://www.hpe.com/psnow/doc/a50004290enw",
    "datasheet"
   ]
  },
  "netto_vk": "80.00"
 },
 "R8R46A": {
  "_facts": {
   "unterkategorie": "Unmanaged Switch",
   "quell_url": "https://www.hpe.com/psnow/doc/a50004290enw",
   "verifiziert_am": "2026-07-02"
  },
  "artikelname": "Aruba Instant On 1430 8G Class4 PoE 64W R8R46A Unmanaged Switch (L2) – 8× 10/100/1000 (RJ45, Class 4 PoE), Desktop-/1-HE-Rackmontage",
  "titel_tag": "Aruba Instant On 1430 8G Class4 PoE 64W R8R46A | Hexwaren",
  "meta_description": "Original Aruba Instant On 1430 8G Class4 PoE 64W (R8R46A): unmanaged Layer-2-Switch mit 8× 10/100/1000 (RJ45, Class 4 PoE), Switching-Kapazität 16 Gbit/s, PoE-Budget 64 W, Plug-and-Play.",
  "artikelgewicht": "0,77",
  "versandgewicht": "2,77",
  "kurzbeschreibung": "<p>Der Aruba Instant On 1430 8G Class4 PoE 64W (R8R46A) ist ein unmanaged Layer-2-Switch der Aruba-Instant-On-1430-Serie mit 8 Ports, verwaltet ohne Konfiguration im Plug-and-Play-Betrieb.</p><p>Im Formfaktor Desktop-/1-HE-Rackmontage liefert der R8R46A eine Switching-Kapazität von 16 Gbit/s und bindet per seine Gigabit-Ports an das Netz an. Über Power over Ethernet versorgt der R8R46A angeschlossene Endgeräte direkt per Netzwerkkabel. Er wird als versiegelte Original-Neuware geliefert.</p>",
  "intro": [
   "Der Aruba Instant On 1430 8G Class4 PoE 64W (R8R46A) ist ein unmanaged Layer-2-Switch aus der Aruba-Instant-On-1430-Familie mit 8 Ports (8× 10/100/1000 (RJ45, Class 4 PoE)), ausgelegt für den einfachen, konfigurationsfreien Netzzugang.",
   "Mit 8 Ports erreicht der R8R46A eine Switching-Kapazität von 16 Gbit/s bei einer Weiterleitungsrate von 11,90 Mpps. Der R8R46A versorgt Access Points, IP-Telefone und Kameras per Power over Ethernet direkt über das Netzwerkkabel. Der R8R46A arbeitet als Plug-and-Play-Gerät ohne Management: keine Konfiguration, kein VLAN-Setup und kein Stacking – einstecken und betreiben.",
   "Im Formfaktor Desktop-/1-HE-Rackmontage arbeitet der R8R46A im Temperaturbereich 0 bis 40 °C; für Kühlung und Stromversorgung des R8R46A sorgen Lüfterlos (passiv gekühlt) sowie Externes Steckernetzteil (im Lieferumfang). Der R8R46A bietet Layer-2-Plug-and-Play-Weiterleitung mit automatischem QoS (802.1p/DSCP), Flusssteuerung, Jumbo-Frames und Energy Efficient Ethernet – ohne Konfiguration. Geliefert wird der R8R46A als versiegelte Original-Neuware. Originaler HP-Switch."
  ],
  "kompatibilitaet": [
   "Plug-and-Play (kein Management erforderlich)"
  ],
  "faq": [
   [
    "Wie viele Ports hat der R8R46A?",
    "Der R8R46A bietet insgesamt 8 Ports: 8× 10/100/1000 (RJ45, Class 4 PoE)."
   ],
   [
    "Unterstützt der R8R46A PoE?",
    "Ja. Der R8R46A stellt Ja (IEEE 802.3at Class 4 PoE+, 30 W/Port, Budget 64 W) bereit und versorgt angeschlossene Geräte direkt über das Netzwerkkabel."
   ],
   [
    "Muss der R8R46A konfiguriert werden?",
    "Nein. Der R8R46A ist ein Unmanaged-Switch und arbeitet ohne Konfiguration im Plug-and-Play-Betrieb."
   ],
   [
    "Was zeichnet den R8R46A technisch aus?",
    "Der R8R46A bietet eine Switching-Kapazität von 16 Gbit/s und eine Weiterleitungsrate von 11,90 Mpps. Er bietet Layer-2-Plug-and-Play-Weiterleitung mit automatischem QoS (802.1p/DSCP), Flusssteuerung, Jumbo-Frames und Energy Efficient Ethernet – ohne Konfiguration. Für Stromversorgung und Kühlung des R8R46A sorgen Externes Steckernetzteil (im Lieferumfang) sowie Lüfterlos (passiv gekühlt)."
   ]
  ],
  "verwandte": [],
  "attributes": [
   [
    "Switch-Typ",
    "Unmanaged"
   ],
   [
    "Layer",
    "L2"
   ],
   [
    "Portanzahl",
    "8"
   ],
   [
    "Port-Konfiguration",
    "8× 10/100/1000 (RJ45, Class 4 PoE)"
   ],
   [
    "Port-Geschwindigkeit",
    "10/100/1000 Mbit/s (RJ45)"
   ],
   [
    "Uplink-Ports",
    "Kein dedizierter Uplink (alle Ports gleichwertig nutzbar)"
   ],
   [
    "PoE",
    "Ja (IEEE 802.3at Class 4 PoE+, 30 W/Port, Budget 64 W)"
   ],
   [
    "Switching-Kapazität",
    "16 Gbit/s"
   ],
   [
    "Durchsatz",
    "11,90 Mpps"
   ],
   [
    "Bauform",
    "Desktop-/1-HE-Rackmontage (kompakt)"
   ],
   [
    "Stromversorgung",
    "Externes Steckernetzteil (im Lieferumfang)"
   ],
   [
    "Kühlung",
    "Lüfterlos (passiv gekühlt)"
   ],
   [
    "Betriebstemperatur",
    "0 bis 40 °C"
   ],
   [
    "Anwendung",
    "Unmanaged SMB-/Heimbüro-Zugang (Layer 2, Plug-and-Play) ohne Management, für einfache Netzerweiterung"
   ],
   [
    "Zustand",
    "Neu, versiegelt"
   ]
  ],
  "provenance": {
   "Switch-Typ": [
    "https://www.hpe.com/psnow/doc/a50004290enw",
    "datasheet"
   ],
   "Layer": [
    "https://www.hpe.com/psnow/doc/a50004290enw",
    "datasheet"
   ],
   "Portanzahl": [
    "https://www.hpe.com/psnow/doc/a50004290enw",
    "datasheet"
   ],
   "Port-Konfiguration": [
    "https://www.hpe.com/psnow/doc/a50004290enw",
    "datasheet"
   ],
   "Port-Geschwindigkeit": [
    "https://www.hpe.com/psnow/doc/a50004290enw",
    "datasheet"
   ],
   "Uplink-Ports": [
    "https://www.hpe.com/psnow/doc/a50004290enw",
    "datasheet"
   ],
   "PoE": [
    "https://www.hpe.com/psnow/doc/a50004290enw",
    "datasheet"
   ],
   "Switching-Kapazität": [
    "https://www.hpe.com/psnow/doc/a50004290enw",
    "datasheet"
   ],
   "Durchsatz": [
    "https://www.hpe.com/psnow/doc/a50004290enw",
    "datasheet"
   ],
   "Bauform": [
    "https://www.hpe.com/psnow/doc/a50004290enw",
    "datasheet"
   ],
   "Stromversorgung": [
    "https://www.hpe.com/psnow/doc/a50004290enw",
    "datasheet"
   ],
   "Kühlung": [
    "https://www.hpe.com/psnow/doc/a50004290enw",
    "datasheet"
   ],
   "Betriebstemperatur": [
    "https://www.hpe.com/psnow/doc/a50004290enw",
    "datasheet"
   ],
   "Anwendung": [
    "https://www.hpe.com/psnow/doc/a50004290enw",
    "datasheet"
   ]
  },
  "netto_vk": "130.00"
 },
 "R8R47A": {
  "_facts": {
   "unterkategorie": "Unmanaged Switch",
   "quell_url": "https://www.hpe.com/psnow/doc/a50004290enw",
   "verifiziert_am": "2026-07-02"
  },
  "artikelname": "Aruba Instant On 1430 16G R8R47A Unmanaged Switch (L2) – 16× 10/100/1000 (RJ45), 19-Zoll-Rackmontage",
  "titel_tag": "Aruba Instant On 1430 16G R8R47A | Hexwaren",
  "meta_description": "Original Aruba Instant On 1430 16G (R8R47A): unmanaged Layer-2-Switch mit 16× 10/100/1000 (RJ45), Switching-Kapazität 32 Gbit/s, ohne PoE, Plug-and-Play.",
  "artikelgewicht": "1,72",
  "versandgewicht": "3,72",
  "kurzbeschreibung": "<p>Der Aruba Instant On 1430 16G (R8R47A) ist ein unmanaged Layer-2-Switch der Aruba-Instant-On-1430-Serie mit 16 Ports, verwaltet ohne Konfiguration im Plug-and-Play-Betrieb.</p><p>Im Formfaktor 19-Zoll-Rackmontage liefert der R8R47A eine Switching-Kapazität von 32 Gbit/s und bindet per seine Gigabit-Ports an das Netz an. Er wird als versiegelte Original-Neuware geliefert.</p>",
  "intro": [
   "Der Aruba Instant On 1430 16G (R8R47A) ist ein unmanaged Layer-2-Switch aus der Aruba-Instant-On-1430-Familie mit 16 Ports (16× 10/100/1000 (RJ45)), ausgelegt für den einfachen, konfigurationsfreien Netzzugang.",
   "Mit 16 Ports erreicht der R8R47A eine Switching-Kapazität von 32 Gbit/s bei einer Weiterleitungsrate von 23,80 Mpps. Der R8R47A ist ein Modell ohne PoE und konzentriert sich auf reine Datenanbindung. Der R8R47A arbeitet als Plug-and-Play-Gerät ohne Management: keine Konfiguration, kein VLAN-Setup und kein Stacking – einstecken und betreiben.",
   "Im Formfaktor 19-Zoll-Rackmontage arbeitet der R8R47A im Temperaturbereich 0 bis 40 °C; für Kühlung und Stromversorgung des R8R47A sorgen Lüfterlos (passiv gekühlt) sowie Internes Netzteil. Der R8R47A bietet Layer-2-Plug-and-Play-Weiterleitung mit automatischem QoS (802.1p/DSCP), Flusssteuerung, Jumbo-Frames und Energy Efficient Ethernet – ohne Konfiguration. Geliefert wird der R8R47A als versiegelte Original-Neuware. Originaler HP-Switch."
  ],
  "kompatibilitaet": [
   "Plug-and-Play (kein Management erforderlich)"
  ],
  "faq": [
   [
    "Wie viele Ports hat der R8R47A?",
    "Der R8R47A bietet insgesamt 16 Ports: 16× 10/100/1000 (RJ45)."
   ],
   [
    "Unterstützt der R8R47A PoE?",
    "Nein. Der R8R47A ist ein Modell ohne Power over Ethernet und für reine Datenanbindung ausgelegt."
   ],
   [
    "Muss der R8R47A konfiguriert werden?",
    "Nein. Der R8R47A ist ein Unmanaged-Switch und arbeitet ohne Konfiguration im Plug-and-Play-Betrieb."
   ],
   [
    "Was zeichnet den R8R47A technisch aus?",
    "Der R8R47A bietet eine Switching-Kapazität von 32 Gbit/s und eine Weiterleitungsrate von 23,80 Mpps. Er bietet Layer-2-Plug-and-Play-Weiterleitung mit automatischem QoS (802.1p/DSCP), Flusssteuerung, Jumbo-Frames und Energy Efficient Ethernet – ohne Konfiguration. Für Stromversorgung und Kühlung des R8R47A sorgen Internes Netzteil sowie Lüfterlos (passiv gekühlt)."
   ]
  ],
  "verwandte": [],
  "attributes": [
   [
    "Switch-Typ",
    "Unmanaged"
   ],
   [
    "Layer",
    "L2"
   ],
   [
    "Portanzahl",
    "16"
   ],
   [
    "Port-Konfiguration",
    "16× 10/100/1000 (RJ45)"
   ],
   [
    "Port-Geschwindigkeit",
    "10/100/1000 Mbit/s (RJ45)"
   ],
   [
    "Uplink-Ports",
    "Kein dedizierter Uplink (alle Ports gleichwertig nutzbar)"
   ],
   [
    "PoE",
    "Nein"
   ],
   [
    "Switching-Kapazität",
    "32 Gbit/s"
   ],
   [
    "Durchsatz",
    "23,80 Mpps"
   ],
   [
    "Bauform",
    "19-Zoll-Rackmontage (1 HE)"
   ],
   [
    "Stromversorgung",
    "Internes Netzteil"
   ],
   [
    "Kühlung",
    "Lüfterlos (passiv gekühlt)"
   ],
   [
    "Betriebstemperatur",
    "0 bis 40 °C"
   ],
   [
    "Anwendung",
    "Unmanaged SMB-/Heimbüro-Zugang (Layer 2, Plug-and-Play) ohne Management, für einfache Netzerweiterung"
   ],
   [
    "Zustand",
    "Neu, versiegelt"
   ]
  ],
  "provenance": {
   "Switch-Typ": [
    "https://www.hpe.com/psnow/doc/a50004290enw",
    "datasheet"
   ],
   "Layer": [
    "https://www.hpe.com/psnow/doc/a50004290enw",
    "datasheet"
   ],
   "Portanzahl": [
    "https://www.hpe.com/psnow/doc/a50004290enw",
    "datasheet"
   ],
   "Port-Konfiguration": [
    "https://www.hpe.com/psnow/doc/a50004290enw",
    "datasheet"
   ],
   "Port-Geschwindigkeit": [
    "https://www.hpe.com/psnow/doc/a50004290enw",
    "datasheet"
   ],
   "Uplink-Ports": [
    "https://www.hpe.com/psnow/doc/a50004290enw",
    "datasheet"
   ],
   "PoE": [
    "https://www.hpe.com/psnow/doc/a50004290enw",
    "datasheet"
   ],
   "Switching-Kapazität": [
    "https://www.hpe.com/psnow/doc/a50004290enw",
    "datasheet"
   ],
   "Durchsatz": [
    "https://www.hpe.com/psnow/doc/a50004290enw",
    "datasheet"
   ],
   "Bauform": [
    "https://www.hpe.com/psnow/doc/a50004290enw",
    "datasheet"
   ],
   "Stromversorgung": [
    "https://www.hpe.com/psnow/doc/a50004290enw",
    "datasheet"
   ],
   "Kühlung": [
    "https://www.hpe.com/psnow/doc/a50004290enw",
    "datasheet"
   ],
   "Betriebstemperatur": [
    "https://www.hpe.com/psnow/doc/a50004290enw",
    "datasheet"
   ],
   "Anwendung": [
    "https://www.hpe.com/psnow/doc/a50004290enw",
    "datasheet"
   ]
  },
  "netto_vk": "140.00"
 },
 "R8R48A": {
  "_facts": {
   "unterkategorie": "Unmanaged Switch",
   "quell_url": "https://www.hpe.com/psnow/doc/a50004290enw",
   "verifiziert_am": "2026-07-02"
  },
  "artikelname": "Aruba Instant On 1430 16G Class4 PoE 124W R8R48A Unmanaged Switch (L2) – 16× 10/100/1000 (RJ45, Class 4 PoE), 19-Zoll-Rackmontage",
  "titel_tag": "Aruba Instant On 1430 16G Class4 PoE 124W R8R48A | Hexwaren",
  "meta_description": "Original Aruba Instant On 1430 16G Class4 PoE 124W (R8R48A): unmanaged Layer-2-Switch mit 16× 10/100/1000 (RJ45, Class 4 PoE), Switching-Kapazität 32 Gbit/s, PoE-Budget 124 W, Plug-and-Play.",
  "artikelgewicht": "2,09",
  "versandgewicht": "4,09",
  "kurzbeschreibung": "<p>Der Aruba Instant On 1430 16G Class4 PoE 124W (R8R48A) ist ein unmanaged Layer-2-Switch der Aruba-Instant-On-1430-Serie mit 16 Ports, verwaltet ohne Konfiguration im Plug-and-Play-Betrieb.</p><p>Im Formfaktor 19-Zoll-Rackmontage liefert der R8R48A eine Switching-Kapazität von 32 Gbit/s und bindet per seine Gigabit-Ports an das Netz an. Über Power over Ethernet versorgt der R8R48A angeschlossene Endgeräte direkt per Netzwerkkabel. Er wird als versiegelte Original-Neuware geliefert.</p>",
  "intro": [
   "Der Aruba Instant On 1430 16G Class4 PoE 124W (R8R48A) ist ein unmanaged Layer-2-Switch aus der Aruba-Instant-On-1430-Familie mit 16 Ports (16× 10/100/1000 (RJ45, Class 4 PoE)), ausgelegt für den einfachen, konfigurationsfreien Netzzugang.",
   "Mit 16 Ports erreicht der R8R48A eine Switching-Kapazität von 32 Gbit/s bei einer Weiterleitungsrate von 23,80 Mpps. Der R8R48A versorgt Access Points, IP-Telefone und Kameras per Power over Ethernet direkt über das Netzwerkkabel. Der R8R48A arbeitet als Plug-and-Play-Gerät ohne Management: keine Konfiguration, kein VLAN-Setup und kein Stacking – einstecken und betreiben.",
   "Im Formfaktor 19-Zoll-Rackmontage arbeitet der R8R48A im Temperaturbereich 0 bis 40 °C; für Kühlung und Stromversorgung des R8R48A sorgen Lüfterlos (passiv gekühlt) sowie Internes Netzteil. Der R8R48A bietet Layer-2-Plug-and-Play-Weiterleitung mit automatischem QoS (802.1p/DSCP), Flusssteuerung, Jumbo-Frames und Energy Efficient Ethernet – ohne Konfiguration. Geliefert wird der R8R48A als versiegelte Original-Neuware. Originaler HP-Switch."
  ],
  "kompatibilitaet": [
   "Plug-and-Play (kein Management erforderlich)"
  ],
  "faq": [
   [
    "Wie viele Ports hat der R8R48A?",
    "Der R8R48A bietet insgesamt 16 Ports: 16× 10/100/1000 (RJ45, Class 4 PoE)."
   ],
   [
    "Unterstützt der R8R48A PoE?",
    "Ja. Der R8R48A stellt Ja (IEEE 802.3at Class 4 PoE+, 30 W/Port, Budget 124 W) bereit und versorgt angeschlossene Geräte direkt über das Netzwerkkabel."
   ],
   [
    "Muss der R8R48A konfiguriert werden?",
    "Nein. Der R8R48A ist ein Unmanaged-Switch und arbeitet ohne Konfiguration im Plug-and-Play-Betrieb."
   ],
   [
    "Was zeichnet den R8R48A technisch aus?",
    "Der R8R48A bietet eine Switching-Kapazität von 32 Gbit/s und eine Weiterleitungsrate von 23,80 Mpps. Er bietet Layer-2-Plug-and-Play-Weiterleitung mit automatischem QoS (802.1p/DSCP), Flusssteuerung, Jumbo-Frames und Energy Efficient Ethernet – ohne Konfiguration. Für Stromversorgung und Kühlung des R8R48A sorgen Internes Netzteil sowie Lüfterlos (passiv gekühlt)."
   ]
  ],
  "verwandte": [],
  "attributes": [
   [
    "Switch-Typ",
    "Unmanaged"
   ],
   [
    "Layer",
    "L2"
   ],
   [
    "Portanzahl",
    "16"
   ],
   [
    "Port-Konfiguration",
    "16× 10/100/1000 (RJ45, Class 4 PoE)"
   ],
   [
    "Port-Geschwindigkeit",
    "10/100/1000 Mbit/s (RJ45)"
   ],
   [
    "Uplink-Ports",
    "Kein dedizierter Uplink (alle Ports gleichwertig nutzbar)"
   ],
   [
    "PoE",
    "Ja (IEEE 802.3at Class 4 PoE+, 30 W/Port, Budget 124 W)"
   ],
   [
    "Switching-Kapazität",
    "32 Gbit/s"
   ],
   [
    "Durchsatz",
    "23,80 Mpps"
   ],
   [
    "Bauform",
    "19-Zoll-Rackmontage (1 HE)"
   ],
   [
    "Stromversorgung",
    "Internes Netzteil"
   ],
   [
    "Kühlung",
    "Lüfterlos (passiv gekühlt)"
   ],
   [
    "Betriebstemperatur",
    "0 bis 40 °C"
   ],
   [
    "Anwendung",
    "Unmanaged SMB-/Heimbüro-Zugang (Layer 2, Plug-and-Play) ohne Management, für einfache Netzerweiterung"
   ],
   [
    "Zustand",
    "Neu, versiegelt"
   ]
  ],
  "provenance": {
   "Switch-Typ": [
    "https://www.hpe.com/psnow/doc/a50004290enw",
    "datasheet"
   ],
   "Layer": [
    "https://www.hpe.com/psnow/doc/a50004290enw",
    "datasheet"
   ],
   "Portanzahl": [
    "https://www.hpe.com/psnow/doc/a50004290enw",
    "datasheet"
   ],
   "Port-Konfiguration": [
    "https://www.hpe.com/psnow/doc/a50004290enw",
    "datasheet"
   ],
   "Port-Geschwindigkeit": [
    "https://www.hpe.com/psnow/doc/a50004290enw",
    "datasheet"
   ],
   "Uplink-Ports": [
    "https://www.hpe.com/psnow/doc/a50004290enw",
    "datasheet"
   ],
   "PoE": [
    "https://www.hpe.com/psnow/doc/a50004290enw",
    "datasheet"
   ],
   "Switching-Kapazität": [
    "https://www.hpe.com/psnow/doc/a50004290enw",
    "datasheet"
   ],
   "Durchsatz": [
    "https://www.hpe.com/psnow/doc/a50004290enw",
    "datasheet"
   ],
   "Bauform": [
    "https://www.hpe.com/psnow/doc/a50004290enw",
    "datasheet"
   ],
   "Stromversorgung": [
    "https://www.hpe.com/psnow/doc/a50004290enw",
    "datasheet"
   ],
   "Kühlung": [
    "https://www.hpe.com/psnow/doc/a50004290enw",
    "datasheet"
   ],
   "Betriebstemperatur": [
    "https://www.hpe.com/psnow/doc/a50004290enw",
    "datasheet"
   ],
   "Anwendung": [
    "https://www.hpe.com/psnow/doc/a50004290enw",
    "datasheet"
   ]
  },
  "netto_vk": "240.00"
 },
 "R8R49A": {
  "_facts": {
   "unterkategorie": "Unmanaged Switch",
   "quell_url": "https://www.hpe.com/psnow/doc/a50004290enw",
   "verifiziert_am": "2026-07-02"
  },
  "artikelname": "Aruba Instant On 1430 24G R8R49A Unmanaged Switch (L2) – 24× 10/100/1000 (RJ45), 19-Zoll-Rackmontage",
  "titel_tag": "Aruba Instant On 1430 24G R8R49A | Hexwaren",
  "meta_description": "Original Aruba Instant On 1430 24G (R8R49A): unmanaged Layer-2-Switch mit 24× 10/100/1000 (RJ45), Switching-Kapazität 48 Gbit/s, ohne PoE, Plug-and-Play.",
  "artikelgewicht": "1,91",
  "versandgewicht": "3,91",
  "kurzbeschreibung": "<p>Der Aruba Instant On 1430 24G (R8R49A) ist ein unmanaged Layer-2-Switch der Aruba-Instant-On-1430-Serie mit 24 Ports, verwaltet ohne Konfiguration im Plug-and-Play-Betrieb.</p><p>Im Formfaktor 19-Zoll-Rackmontage liefert der R8R49A eine Switching-Kapazität von 48 Gbit/s und bindet per seine Gigabit-Ports an das Netz an. Er wird als versiegelte Original-Neuware geliefert.</p>",
  "intro": [
   "Der Aruba Instant On 1430 24G (R8R49A) ist ein unmanaged Layer-2-Switch aus der Aruba-Instant-On-1430-Familie mit 24 Ports (24× 10/100/1000 (RJ45)), ausgelegt für den einfachen, konfigurationsfreien Netzzugang.",
   "Mit 24 Ports erreicht der R8R49A eine Switching-Kapazität von 48 Gbit/s bei einer Weiterleitungsrate von 35,71 Mpps. Der R8R49A ist ein Modell ohne PoE und konzentriert sich auf reine Datenanbindung. Der R8R49A arbeitet als Plug-and-Play-Gerät ohne Management: keine Konfiguration, kein VLAN-Setup und kein Stacking – einstecken und betreiben.",
   "Im Formfaktor 19-Zoll-Rackmontage arbeitet der R8R49A im Temperaturbereich 0 bis 40 °C; für Kühlung und Stromversorgung des R8R49A sorgen Lüfterlos (passiv gekühlt) sowie Internes Netzteil. Der R8R49A bietet Layer-2-Plug-and-Play-Weiterleitung mit automatischem QoS (802.1p/DSCP), Flusssteuerung, Jumbo-Frames und Energy Efficient Ethernet – ohne Konfiguration. Geliefert wird der R8R49A als versiegelte Original-Neuware. Originaler HP-Switch."
  ],
  "kompatibilitaet": [
   "Plug-and-Play (kein Management erforderlich)"
  ],
  "faq": [
   [
    "Wie viele Ports hat der R8R49A?",
    "Der R8R49A bietet insgesamt 24 Ports: 24× 10/100/1000 (RJ45)."
   ],
   [
    "Unterstützt der R8R49A PoE?",
    "Nein. Der R8R49A ist ein Modell ohne Power over Ethernet und für reine Datenanbindung ausgelegt."
   ],
   [
    "Muss der R8R49A konfiguriert werden?",
    "Nein. Der R8R49A ist ein Unmanaged-Switch und arbeitet ohne Konfiguration im Plug-and-Play-Betrieb."
   ],
   [
    "Was zeichnet den R8R49A technisch aus?",
    "Der R8R49A bietet eine Switching-Kapazität von 48 Gbit/s und eine Weiterleitungsrate von 35,71 Mpps. Er bietet Layer-2-Plug-and-Play-Weiterleitung mit automatischem QoS (802.1p/DSCP), Flusssteuerung, Jumbo-Frames und Energy Efficient Ethernet – ohne Konfiguration. Für Stromversorgung und Kühlung des R8R49A sorgen Internes Netzteil sowie Lüfterlos (passiv gekühlt)."
   ]
  ],
  "verwandte": [],
  "attributes": [
   [
    "Switch-Typ",
    "Unmanaged"
   ],
   [
    "Layer",
    "L2"
   ],
   [
    "Portanzahl",
    "24"
   ],
   [
    "Port-Konfiguration",
    "24× 10/100/1000 (RJ45)"
   ],
   [
    "Port-Geschwindigkeit",
    "10/100/1000 Mbit/s (RJ45)"
   ],
   [
    "Uplink-Ports",
    "Kein dedizierter Uplink (alle Ports gleichwertig nutzbar)"
   ],
   [
    "PoE",
    "Nein"
   ],
   [
    "Switching-Kapazität",
    "48 Gbit/s"
   ],
   [
    "Durchsatz",
    "35,71 Mpps"
   ],
   [
    "Bauform",
    "19-Zoll-Rackmontage (1 HE)"
   ],
   [
    "Stromversorgung",
    "Internes Netzteil"
   ],
   [
    "Kühlung",
    "Lüfterlos (passiv gekühlt)"
   ],
   [
    "Betriebstemperatur",
    "0 bis 40 °C"
   ],
   [
    "Anwendung",
    "Unmanaged SMB-/Heimbüro-Zugang (Layer 2, Plug-and-Play) ohne Management, für einfache Netzerweiterung"
   ],
   [
    "Zustand",
    "Neu, versiegelt"
   ]
  ],
  "provenance": {
   "Switch-Typ": [
    "https://www.hpe.com/psnow/doc/a50004290enw",
    "datasheet"
   ],
   "Layer": [
    "https://www.hpe.com/psnow/doc/a50004290enw",
    "datasheet"
   ],
   "Portanzahl": [
    "https://www.hpe.com/psnow/doc/a50004290enw",
    "datasheet"
   ],
   "Port-Konfiguration": [
    "https://www.hpe.com/psnow/doc/a50004290enw",
    "datasheet"
   ],
   "Port-Geschwindigkeit": [
    "https://www.hpe.com/psnow/doc/a50004290enw",
    "datasheet"
   ],
   "Uplink-Ports": [
    "https://www.hpe.com/psnow/doc/a50004290enw",
    "datasheet"
   ],
   "PoE": [
    "https://www.hpe.com/psnow/doc/a50004290enw",
    "datasheet"
   ],
   "Switching-Kapazität": [
    "https://www.hpe.com/psnow/doc/a50004290enw",
    "datasheet"
   ],
   "Durchsatz": [
    "https://www.hpe.com/psnow/doc/a50004290enw",
    "datasheet"
   ],
   "Bauform": [
    "https://www.hpe.com/psnow/doc/a50004290enw",
    "datasheet"
   ],
   "Stromversorgung": [
    "https://www.hpe.com/psnow/doc/a50004290enw",
    "datasheet"
   ],
   "Kühlung": [
    "https://www.hpe.com/psnow/doc/a50004290enw",
    "datasheet"
   ],
   "Betriebstemperatur": [
    "https://www.hpe.com/psnow/doc/a50004290enw",
    "datasheet"
   ],
   "Anwendung": [
    "https://www.hpe.com/psnow/doc/a50004290enw",
    "datasheet"
   ]
  },
  "netto_vk": "200.00"
 },
 "R8R50A": {
  "_facts": {
   "unterkategorie": "Unmanaged Switch",
   "quell_url": "https://www.hpe.com/psnow/doc/a50004290enw",
   "verifiziert_am": "2026-07-02"
  },
  "artikelname": "Aruba Instant On 1430 26G 2SFP R8R50A Unmanaged Switch (L2) – 26× 10/100/1000 (RJ45) + 2× 1G SFP, 19-Zoll-Rackmontage",
  "titel_tag": "Aruba Instant On 1430 26G 2SFP R8R50A | Hexwaren",
  "meta_description": "Original Aruba Instant On 1430 26G 2SFP (R8R50A): unmanaged Layer-2-Switch mit 26× 10/100/1000 (RJ45), Switching-Kapazität 56 Gbit/s, ohne PoE, Plug-and-Play.",
  "artikelgewicht": "2,27",
  "versandgewicht": "4,27",
  "kurzbeschreibung": "<p>Der Aruba Instant On 1430 26G 2SFP (R8R50A) ist ein unmanaged Layer-2-Switch der Aruba-Instant-On-1430-Serie mit 28 Ports, verwaltet ohne Konfiguration im Plug-and-Play-Betrieb.</p><p>Im Formfaktor 19-Zoll-Rackmontage liefert der R8R50A eine Switching-Kapazität von 56 Gbit/s und bindet per 2× 1G SFP an das Netz an. Er wird als versiegelte Original-Neuware geliefert.</p>",
  "intro": [
   "Der Aruba Instant On 1430 26G 2SFP (R8R50A) ist ein unmanaged Layer-2-Switch aus der Aruba-Instant-On-1430-Familie mit 28 Ports (26× 10/100/1000 (RJ45)), ausgelegt für den einfachen, konfigurationsfreien Netzzugang.",
   "Mit 28 Ports erreicht der R8R50A eine Switching-Kapazität von 56 Gbit/s bei einer Weiterleitungsrate von 41,68 Mpps. Der R8R50A ist ein Modell ohne PoE und konzentriert sich auf reine Datenanbindung. Der R8R50A arbeitet als Plug-and-Play-Gerät ohne Management: keine Konfiguration, kein VLAN-Setup und kein Stacking – einstecken und betreiben.",
   "Im Formfaktor 19-Zoll-Rackmontage arbeitet der R8R50A im Temperaturbereich 0 bis 40 °C; für Kühlung und Stromversorgung des R8R50A sorgen Lüfterlos (passiv gekühlt) sowie Internes Netzteil. Der R8R50A bietet Layer-2-Plug-and-Play-Weiterleitung mit automatischem QoS (802.1p/DSCP), Flusssteuerung, Jumbo-Frames und Energy Efficient Ethernet – ohne Konfiguration. Geliefert wird der R8R50A als versiegelte Original-Neuware. Originaler HP-Switch."
  ],
  "kompatibilitaet": [
   "Plug-and-Play (kein Management erforderlich)"
  ],
  "faq": [
   [
    "Wie viele Ports hat der R8R50A?",
    "Der R8R50A bietet insgesamt 28 Ports: 26× 10/100/1000 (RJ45) + 2× 1G SFP (Uplink)."
   ],
   [
    "Unterstützt der R8R50A PoE?",
    "Nein. Der R8R50A ist ein Modell ohne Power over Ethernet und für reine Datenanbindung ausgelegt."
   ],
   [
    "Muss der R8R50A konfiguriert werden?",
    "Nein. Der R8R50A ist ein Unmanaged-Switch und arbeitet ohne Konfiguration im Plug-and-Play-Betrieb."
   ],
   [
    "Was zeichnet den R8R50A technisch aus?",
    "Der R8R50A bietet eine Switching-Kapazität von 56 Gbit/s und eine Weiterleitungsrate von 41,68 Mpps. Er bietet Layer-2-Plug-and-Play-Weiterleitung mit automatischem QoS (802.1p/DSCP), Flusssteuerung, Jumbo-Frames und Energy Efficient Ethernet – ohne Konfiguration. Für Stromversorgung und Kühlung des R8R50A sorgen Internes Netzteil sowie Lüfterlos (passiv gekühlt)."
   ]
  ],
  "verwandte": [],
  "attributes": [
   [
    "Switch-Typ",
    "Unmanaged"
   ],
   [
    "Layer",
    "L2"
   ],
   [
    "Portanzahl",
    "28"
   ],
   [
    "Port-Konfiguration",
    "26× 10/100/1000 (RJ45) + 2× 1G SFP (Uplink)"
   ],
   [
    "Port-Geschwindigkeit",
    "10/100/1000 Mbit/s (RJ45), 1 GbE (SFP)"
   ],
   [
    "Uplink-Ports",
    "2× 1G SFP"
   ],
   [
    "PoE",
    "Nein"
   ],
   [
    "Switching-Kapazität",
    "56 Gbit/s"
   ],
   [
    "Durchsatz",
    "41,68 Mpps"
   ],
   [
    "Bauform",
    "19-Zoll-Rackmontage (1 HE)"
   ],
   [
    "Stromversorgung",
    "Internes Netzteil"
   ],
   [
    "Kühlung",
    "Lüfterlos (passiv gekühlt)"
   ],
   [
    "Betriebstemperatur",
    "0 bis 40 °C"
   ],
   [
    "Anwendung",
    "Unmanaged SMB-/Heimbüro-Zugang (Layer 2, Plug-and-Play) ohne Management, für einfache Netzerweiterung"
   ],
   [
    "Zustand",
    "Neu, versiegelt"
   ]
  ],
  "provenance": {
   "Switch-Typ": [
    "https://www.hpe.com/psnow/doc/a50004290enw",
    "datasheet"
   ],
   "Layer": [
    "https://www.hpe.com/psnow/doc/a50004290enw",
    "datasheet"
   ],
   "Portanzahl": [
    "https://www.hpe.com/psnow/doc/a50004290enw",
    "datasheet"
   ],
   "Port-Konfiguration": [
    "https://www.hpe.com/psnow/doc/a50004290enw",
    "datasheet"
   ],
   "Port-Geschwindigkeit": [
    "https://www.hpe.com/psnow/doc/a50004290enw",
    "datasheet"
   ],
   "Uplink-Ports": [
    "https://www.hpe.com/psnow/doc/a50004290enw",
    "datasheet"
   ],
   "PoE": [
    "https://www.hpe.com/psnow/doc/a50004290enw",
    "datasheet"
   ],
   "Switching-Kapazität": [
    "https://www.hpe.com/psnow/doc/a50004290enw",
    "datasheet"
   ],
   "Durchsatz": [
    "https://www.hpe.com/psnow/doc/a50004290enw",
    "datasheet"
   ],
   "Bauform": [
    "https://www.hpe.com/psnow/doc/a50004290enw",
    "datasheet"
   ],
   "Stromversorgung": [
    "https://www.hpe.com/psnow/doc/a50004290enw",
    "datasheet"
   ],
   "Kühlung": [
    "https://www.hpe.com/psnow/doc/a50004290enw",
    "datasheet"
   ],
   "Betriebstemperatur": [
    "https://www.hpe.com/psnow/doc/a50004290enw",
    "datasheet"
   ],
   "Anwendung": [
    "https://www.hpe.com/psnow/doc/a50004290enw",
    "datasheet"
   ]
  },
  "netto_vk": "280.00"
 }
}